iqdma/__init__.py
iqdma/_version.py
iqdma/data_table.py
iqdma/dialogs.py
iqdma/exporter.py
iqdma/importer.py
iqdma/main.py
iqdma/options.py
iqdma/paths.py
iqdma/pdf_miner.py
iqdma/plot.py
iqdma/stats.py
iqdma/utilities.py
iqdma/utilities_dvha_stats.py
iqdma/windows_reg_edit.py
iqdma/resources/LICENSE.txt
iqdma/resources/csv_templates/IBA_MyQA.json
iqdma/resources/csv_templates/VarianPortalDosimetry.json
iqdma/resources/icons/iconfinder_Close_1493281.png
iqdma/resources/icons/iconfinder_Files_Search_4903885.png
iqdma/resources/icons/iconfinder_Open_1493293.png
iqdma/resources/icons/iconfinder_Save_1493294.png
iqdma/resources/icons/iconfinder_Settings_1493289.png
iqdma/resources/icons/iqdma.icns
iqdma/resources/icons/iqdma.ico
iqdma/resources/icons/iqdma_frame.ico
iqdma-0.1.9.dist-info/LICENSE
iqdma-0.1.9.dist-info/METADATA
iqdma-0.1.9.dist-info/WHEEL
iqdma-0.1.9.dist-info/entry_points.txt
iqdma-0.1.9.dist-info/top_level.txt
iqdma-0.1.9.dist-info/RECORD
