Metadata-Version: 2.1
Name: iqdma
Version: 0.1.9
Summary: Analyze IMRT QA Report data mined with IQDM-PDF
Home-page: https://github.com/IQDM/IQDM-Analytics
Author: Dan Cutright
Author-email: dan.cutright@gmail.com
License: MIT License
Download-URL: https://github.com/IQDM/IQDM-Analytics/archive/master.zip
Keywords: radiation therapy,research,IMRT QA,bokeh,analytics,wxpython
Platform: UNKNOWN
Requires-Python: >3.5
Requires-Dist: iqdmpdf (>=0.3.0)
Requires-Dist: wxpython
Requires-Dist: bokeh (==1.4.0)
Requires-Dist: numpy
Requires-Dist: selenium
Requires-Dist: pypubsub
Requires-Dist: python-dateutil
